alpyro/__init__.py
alpyro/node.py
alpyro/tcp.py
alpyro/xmlrpc.py
alpyro-2020.8a0.dist-info/LICENSE
alpyro-2020.8a0.dist-info/METADATA
alpyro-2020.8a0.dist-info/WHEEL
alpyro-2020.8a0.dist-info/top_level.txt
alpyro-2020.8a0.dist-info/RECORD
