Metadata-Version: 2.1
Name: alpyro
Version: 2020.8a0
Summary: Alternative ROS client library
Home-page: https://github.com/rho2/alpyro
Author: Robin Brase
Author-email: git@rho2.eu
License: MIT
Platform: UNKNOWN
Classifier: License :: OSI Approved :: MIT License
Classifier: Intended Audience :: Developers
Classifier: Programming Language :: Python :: 3
Classifier: Programming Language :: Python :: 3 :: Only
Classifier: Programming Language :: Python :: 3.8
Requires-Python: >=3.8
Requires-Dist: aiohttp (>=3.6.2)
Requires-Dist: alpyro-msgs
Requires-Dist: typing-extensions (>=3.7.4.2)
